odoo/addons/product_supplierinfo_discount/README.rst
odoo/addons/product_supplierinfo_discount/__init__.py
odoo/addons/product_supplierinfo_discount/__manifest__.py
odoo/addons/product_supplierinfo_discount/i18n/am.po
odoo/addons/product_supplierinfo_discount/i18n/ar.po
odoo/addons/product_supplierinfo_discount/i18n/bg.po
odoo/addons/product_supplierinfo_discount/i18n/bs.po
odoo/addons/product_supplierinfo_discount/i18n/ca.po
odoo/addons/product_supplierinfo_discount/i18n/cs.po
odoo/addons/product_supplierinfo_discount/i18n/da.po
odoo/addons/product_supplierinfo_discount/i18n/de.po
odoo/addons/product_supplierinfo_discount/i18n/el_GR.po
odoo/addons/product_supplierinfo_discount/i18n/en_GB.po
odoo/addons/product_supplierinfo_discount/i18n/es.po
odoo/addons/product_supplierinfo_discount/i18n/es_CR.po
odoo/addons/product_supplierinfo_discount/i18n/es_EC.po
odoo/addons/product_supplierinfo_discount/i18n/es_ES.po
odoo/addons/product_supplierinfo_discount/i18n/es_MX.po
odoo/addons/product_supplierinfo_discount/i18n/es_VE.po
odoo/addons/product_supplierinfo_discount/i18n/et.po
odoo/addons/product_supplierinfo_discount/i18n/eu.po
odoo/addons/product_supplierinfo_discount/i18n/fi.po
odoo/addons/product_supplierinfo_discount/i18n/fr.po
odoo/addons/product_supplierinfo_discount/i18n/fr_CA.po
odoo/addons/product_supplierinfo_discount/i18n/fr_CH.po
odoo/addons/product_supplierinfo_discount/i18n/gl.po
odoo/addons/product_supplierinfo_discount/i18n/hr.po
odoo/addons/product_supplierinfo_discount/i18n/hr_HR.po
odoo/addons/product_supplierinfo_discount/i18n/hu.po
odoo/addons/product_supplierinfo_discount/i18n/it.po
odoo/addons/product_supplierinfo_discount/i18n/ja.po
odoo/addons/product_supplierinfo_discount/i18n/lt.po
odoo/addons/product_supplierinfo_discount/i18n/lv.po
odoo/addons/product_supplierinfo_discount/i18n/mk.po
odoo/addons/product_supplierinfo_discount/i18n/mn.po
odoo/addons/product_supplierinfo_discount/i18n/nb.po
odoo/addons/product_supplierinfo_discount/i18n/nb_NO.po
odoo11_addon_product_supplierinfo_discount-11.0.1.0.0.99.dev7.dist-info/METADATA
odoo11_addon_product_supplierinfo_discount-11.0.1.0.0.99.dev7.dist-info/WHEEL
odoo11_addon_product_supplierinfo_discount-11.0.1.0.0.99.dev7.dist-info/top_level.txt
odoo11_addon_product_supplierinfo_discount-11.0.1.0.0.99.dev7.dist-info/RECORD
